pypcd_imp/__init__.py
pypcd_imp/nea_pc_format.py
pypcd_imp/numpy_pc2.py
pypcd_imp/pdutil.py
pypcd_imp/pypcd.py
pypcd_imp/sautil.py
pypcd_imp/version.py
pypcd_imp/tests/__init__.py
pypcd_imp/tests/test_pypcd.py
pypcd_imp-0.1.5.dist-info/LICENSE
pypcd_imp-0.1.5.dist-info/METADATA
pypcd_imp-0.1.5.dist-info/WHEEL
pypcd_imp-0.1.5.dist-info/top_level.txt
pypcd_imp-0.1.5.dist-info/RECORD
