Metadata-Version: 2.1
Name: pypcd-imp
Version: 0.1.5
Summary: Pure Python PCD reader/writer
Home-page: https://github.com/joelosw/pypcd-imp
Download-URL: 
Author: Daniel Maturana
Author-email: dimatura@cmu.edu
Maintainer: Joel Oswald
Maintainer-email: joel@stefamon.de
License: MIT
Platform: OS Independent
Classifier: Development Status :: 3 - Alpha
Classifier: Environment :: Console
Classifier: Intended Audience :: Science/Research
Classifier: License :: OSI Approved :: MIT License
Classifier: Operating System :: OS Independent
Classifier: Programming Language :: Python
Classifier: Topic :: Scientific/Engineering
License-File: LICENSE
Requires-Dist: numpy
Requires-Dist: python-lzf
